CHANGES.rst
LICENSE.rst
MANIFEST.in
README.rst
setup.py
tox.ini
update_ez_setup.sh
pytest_cram/__init__.py
pytest_cram/compat.py
pytest_cram/version.py
pytest_cram.egg-info/PKG-INFO
pytest_cram.egg-info/SOURCES.txt
pytest_cram.egg-info/dependency_links.txt
pytest_cram.egg-info/entry_points.txt
pytest_cram.egg-info/pbr.json
pytest_cram.egg-info/requires.txt
pytest_cram.egg-info/top_level.txt
pytest_cram/tests/__init__.py
pytest_cram/tests/test_examples.py
pytest_cram/tests/test_options.py