Metadata-Version: 1.1
Name: pytest-cram
Version: 0.2.2
Summary: Run cram tests with pytest.
Home-page: https://github.com/tbekolay/pytest-cram
Author: Trevor Bekolay
Author-email: tbekolay@gmail.com
License: MIT license
Platform: UNKNOWN
Classifier: Framework :: Pytest
Classifier: License :: OSI Approved :: MIT License
Classifier: Programming Language :: Python :: 2.7
Classifier: Programming Language :: Python :: 3.3
Classifier: Programming Language :: Python :: 3.4
Classifier: Programming Language :: Python :: 3.5
Classifier: Topic :: Software Development :: Testing
